[
  {
    "timestamp": "2025-12-06T16:00:57.007944",
    "score": 100,
    "cpu": 2.96,
    "memory": 18.34,
    "disk": 20.3,
    "gpu_mem": 4.851867754401031,
    "alerts_count": 0
  },
  {
    "timestamp": "2025-12-06T18:06:50.591660",
    "score": 100,
    "cpu": 5.5,
    "memory": 19.93,
    "disk": 18.47,
    "gpu_mem": 6.366926332576826,
    "alerts_count": 0
  },
  {
    "timestamp": "2025-12-07T06:00:01.893434",
    "score": 100,
    "cpu": null,
    "memory": null,
    "disk": null,
    "gpu_mem": 4.55130957492486,
    "alerts_count": 0
  },
  {
    "timestamp": "2025-12-08T06:00:01.567699",
    "score": 100,
    "cpu": null,
    "memory": null,
    "disk": null,
    "gpu_mem": 4.391829724590566,
    "alerts_count": 0
  },
  {
    "timestamp": "2025-12-09T06:00:01.440897",
    "score": 100,
    "cpu": null,
    "memory": null,
    "disk": null,
    "gpu_mem": 3.925657854382629,
    "alerts_count": 0
  },
  {
    "timestamp": "2025-12-10T06:00:01.406044",
    "score": 100,
    "cpu": null,
    "memory": null,
    "disk": null,
    "gpu_mem": 3.9992639391523035,
    "alerts_count": 0
  }
]